trendyol-crawler/Crawler.py
trendyol-crawler/__init__.py
trendyol-crawler/models/Menu.py
trendyol-crawler/models/Order.py
trendyol-crawler/models/Product.py
trendyol-crawler/models/Restaurant.py
trendyol-crawler/models/__init__.py
trendyol_crawler/Crawler.py
trendyol_crawler/__init__.py
trendyol_crawler/models/Menu.py
trendyol_crawler/models/Order.py
trendyol_crawler/models/Product.py
trendyol_crawler/models/Restaurant.py
trendyol_crawler/models/__init__.py
trendyol_crawler-1.0.0.dist-info/METADATA
trendyol_crawler-1.0.0.dist-info/WHEEL
trendyol_crawler-1.0.0.dist-info/top_level.txt
trendyol_crawler-1.0.0.dist-info/RECORD
