Metadata-Version: 2.1
Name: trendyol-crawler
Version: 1.0.0
Summary: TRENDYOL CRAWLER
Author: Esat
Author-email: esatyilmaz3500@gmail.com
